datagrid_gtk3-0.1.5.dist-info/pbr.json
datagrid_gtk3-0.1.5.dist-info/WHEEL
datagrid_gtk3-0.1.5.dist-info/METADATA
datagrid_gtk3-0.1.5.dist-info/top_level.txt
datagrid_gtk3-0.1.5.dist-info/DESCRIPTION.rst
datagrid_gtk3-0.1.5.dist-info/metadata.json
datagrid_gtk3-0.1.5.dist-info/RECORD
datagrid_gtk3/__init__.py
datagrid_gtk3/ui/uifile.py
datagrid_gtk3/ui/__init__.py
datagrid_gtk3/ui/grid.py
datagrid_gtk3/ui/popupcal.py
datagrid_gtk3/ui/glade/popupcal.glade
datagrid_gtk3/ui/glade/datagrid.glade
datagrid_gtk3/tests/test_datagrid-gtk3.py
datagrid_gtk3/tests/test_externals.py
datagrid_gtk3/tests/data.py
datagrid_gtk3/tests/__init__.py
datagrid_gtk3/tests/test_sqlite.py
datagrid_gtk3/tests/ui/test_popupcal.py
datagrid_gtk3/tests/ui/__init__.py
datagrid_gtk3/tests/utils/test_dateutils.py
datagrid_gtk3/tests/utils/test_transformations.py
datagrid_gtk3/tests/utils/__init__.py
datagrid_gtk3/tests/utils/test_stringutils.py
datagrid_gtk3/db/sqlite.py
datagrid_gtk3/db/__init__.py
datagrid_gtk3/utils/transformations.py
datagrid_gtk3/utils/imageutils.py
datagrid_gtk3/utils/dateutils.py
datagrid_gtk3/utils/__init__.py
datagrid_gtk3/utils/stringutils.py
datagrid_gtk3/data/README
datagrid_gtk3/data/LICENSE.txt
datagrid_gtk3/data/media/icons/image.png
datagrid_gtk3/data/media/icons/text.png
datagrid_gtk3/data/media/icons/video.png
datagrid_gtk3/data/media/icons/calendar.png
datagrid_gtk3/data/media/icons/audio.png
datagrid_gtk3/data/media/icons/unknown.png
