Metadata-Version: 2.0
Name: datagrid-gtk3
Version: 0.1.5
Summary: MVC framework for working with the GTK3 TreeView widget.
Home-page: https://github.com/nowsecure/datagrid-gtk3
Author: NowSecure
Author-email: info@nowsecure.com
License: MIT
Keywords: mvc sqlite gtk gtk3 grid
Platform: UNKNOWN
Classifier: Natural Language :: English
Classifier: Programming Language :: Python :: 2
Requires-Dist: wheel (>=0.23.0)
Requires-Dist: python-dateutil (>=2.4.2)
Requires-Dist: sqlalchemy (>=0.9)
Requires-Dist: Pillow (>=2.7.0)
